netbox_zabbix/__init__.py
netbox_zabbix/jsonrpc.py
netbox_zabbix/zabbix.py
netbox_zabbix/choices/__init__.py
netbox_zabbix/choices/snmp.py
netbox_zabbix/jobs/__init__.py
netbox_zabbix/jobs/zabbix.py
netbox_zabbix/management/__init__.py
netbox_zabbix/management/commands/__init__.py
netbox_zabbix/management/commands/testapi.py
netbox_zabbix/models/__init__.py
netbox_zabbix/models/device.py
netbox_zabbix/models/snmp.py
netbox_zabbix/models/zabbix.py
netbox_zabbix/signals/__init__.py
netbox_zabbix/signals/device.py
netbox_zabbix/signals/signals.py
netbox_zabbix/utilities/__init__.py
netbox_zabbix/utilities/helper.py
netbox_zabbix/utilities/zabbix.py
netbox_zabbix-2.0.3.dist-info/LICENSE
netbox_zabbix-2.0.3.dist-info/METADATA
netbox_zabbix-2.0.3.dist-info/WHEEL
netbox_zabbix-2.0.3.dist-info/top_level.txt
netbox_zabbix-2.0.3.dist-info/RECORD
