Metadata-Version: 2.1
Name: netbox_zabbix
Version: 2.0.3
Summary: NetBox Zabbix Sync
Home-page: https://github.com/dansheps/netbox-zabbix/
Download-URL: https://github.com/dansheps/netbox-zabbix/
Author: Daniel Sheppard
Author-email: dans@dansheps.com
Maintainer: Daniel Sheppard
Maintainer-email: dans@dansheps.com
License: GNU GPL v3
Keywords: netbox,netbox-plugin
Classifier: Framework :: Django
Classifier: Programming Language :: Python :: 3
License-File: LICENSE
